lib_sync-0.2.2.dist-info/licenses/LICENSE
libsync/__init__.py
libsync/__main__.py
libsync/cli.py
libsync/analyze/analyze_rekordbox_library.py
libsync/analyze/generate_rekordbox_library_report.py
libsync/analyze/get_rekordbox_library.py
libsync/db/db_read_operations.py
libsync/db/db_utils.py
libsync/db/db_write_operations.py
libsync/id/download_audio.py
libsync/id/get_ids_from_recording.py
libsync/id/youtube_dl_utils.py
libsync/spotify/get_spotify_matches.py
libsync/spotify/spotify_api_utils.py
libsync/spotify/spotify_auth.py
libsync/spotify/sync_rekordbox_to_spotify.py
libsync/spotify/sync_spotify_playlists.py
libsync/utils/constants.py
libsync/utils/file_utils.py
libsync/utils/parser_utils.py
libsync/utils/rekordbox_library.py
libsync/utils/similarity_utils.py
libsync/utils/string_utils.py
lib_sync-0.2.2.dist-info/METADATA
lib_sync-0.2.2.dist-info/WHEEL
lib_sync-0.2.2.dist-info/entry_points.txt
lib_sync-0.2.2.dist-info/top_level.txt
lib_sync-0.2.2.dist-info/RECORD
