Metadata-Version: 2.4
Name: lib-sync
Version: 0.2.2
Summary: A collection of tools for managing your music library
Author-email: Josh Lebedinsky <joshlebed@gmail.com>
License-Expression: MIT
Project-URL: Homepage, https://github.com/clobraico22/lib-sync
Requires-Python: >=3.11
License-File: LICENSE
Requires-Dist: spotipy==2.23.0
Requires-Dist: python-dotenv==1.0.0
Requires-Dist: yt-dlp==2025.06.09
Requires-Dist: aiohttp==3.9.3
Requires-Dist: colorama==0.4.6
Requires-Dist: tqdm==4.62.3
Requires-Dist: shazamio==0.7.0
Requires-Dist: ffmpeg-python==0.2.0
Requires-Dist: audioop-lts>=0.2.1; python_version >= "3.13"
Dynamic: license-file
